relbench/__init__.py
relbench/metrics.py
relbench/utils.py
relbench/base/__init__.py
relbench/base/database.py
relbench/base/dataset.py
relbench/base/table.py
relbench/base/task_autocomplete.py
relbench/base/task_base.py
relbench/base/task_entity.py
relbench/base/task_recommendation.py
relbench/datasets/__init__.py
relbench/datasets/amazon.py
relbench/datasets/arxiv.py
relbench/datasets/avito.py
relbench/datasets/dbinfer.py
relbench/datasets/event.py
relbench/datasets/f1.py
relbench/datasets/fake.py
relbench/datasets/hashes.json
relbench/datasets/hm.py
relbench/datasets/mimic.py
relbench/datasets/ratebeer.py
relbench/datasets/salt.py
relbench/datasets/stack.py
relbench/datasets/trial.py
relbench/modeling/__init__.py
relbench/modeling/graph.py
relbench/modeling/loader.py
relbench/modeling/nn.py
relbench/modeling/utils.py
relbench/tasks/__init__.py
relbench/tasks/amazon.py
relbench/tasks/arxiv.py
relbench/tasks/avito.py
relbench/tasks/dbinfer.py
relbench/tasks/event.py
relbench/tasks/f1.py
relbench/tasks/hashes.json
relbench/tasks/hm.py
relbench/tasks/mimic.py
relbench/tasks/ratebeer.py
relbench/tasks/stack.py
relbench/tasks/trial.py
relbench-2.0.2.dist-info/licenses/LICENSE
relbench-2.0.2.dist-info/WHEEL
relbench-2.0.2.dist-info/METADATA
relbench-2.0.2.dist-info/RECORD
