Metadata-Version: 2.4
Name: relbench
Version: 2.0.2
Summary: RelBench: Relational Deep Learning Benchmark
Keywords: 
Author-email: RelBench Team <relbench@cs.stanford.edu>
Requires-Python: >=3.10
Classifier: License :: OSI Approved :: MIT License
License-File: LICENSE
Requires-Dist: pandas
Requires-Dist: pooch
Requires-Dist: pyarrow
Requires-Dist: numpy
Requires-Dist: duckdb
Requires-Dist: scikit-learn<=1.6.1
Requires-Dist: typing-extensions
Requires-Dist: datasets
Requires-Dist: redelex ; extra == "ctu"
Requires-Dist: dbinfer-relbench-adapter ; extra == "dbinfer"
Requires-Dist: pre-commit ; extra == "dev"
Requires-Dist: sentence-transformers ; extra == "example"
Requires-Dist: pytorch_frame[full] ; extra == "example"
Requires-Dist: torch_geometric ; extra == "example"
Requires-Dist: tqdm ; extra == "example"
Requires-Dist: pytorch_frame>=0.2.3 ; extra == "full"
Requires-Dist: torch_geometric ; extra == "full"
Requires-Dist: pytest ; extra == "test"
Project-URL: Home, https://relbench.stanford.edu
Provides-Extra: ctu
Provides-Extra: dbinfer
Provides-Extra: dev
Provides-Extra: example
Provides-Extra: full
Provides-Extra: test
